{"version":1,"resource":"vscode-remote://ujuadimorad-afrikkitche-w2pyx2xzr68.ws-eu101.gitpod.io/workspace/Afrik-kitchen/view_menu/templates/menu/create_menu.html","entries":[{"id":"v4GG.html","timestamp":1688689092661},{"id":"3etV.html","timestamp":1688689336969},{"id":"v6qq.html","timestamp":1688689396309},{"id":"IWYE.html","timestamp":1688690170260},{"id":"JMbO.html","timestamp":1688690243160},{"id":"khJE.html","timestamp":1688693084209},{"id":"5HqP.html","timestamp":1688693190465},{"id":"sLpl.html","source":"moved.source","timestamp":1688693222155},{"id":"tDdA.html","source":"moved.source","timestamp":1688693591129},{"id":"SubP.html","source":"moved.source","timestamp":1688693640239},{"id":"vHOx.html","source":"moved.source","timestamp":1688695235058},{"id":"exoe.html","source":"moved.source","timestamp":1688696431143},{"id":"MthR.html","source":"moved.source","timestamp":1688696980518},{"id":"rtvA.html","source":"moved.source","timestamp":1688698082513},{"id":"exUt.html","source":"moved.source","timestamp":1688698262556},{"id":"OQci.html","source":"moved.source","timestamp":1688699107043},{"id":"dqxo.html","source":"moved.source","timestamp":1688699182816},{"id":"fNLj.html","timestamp":1688699587271}]}